process_pose_data/__init__.py
process_pose_data/geom_render.py
process_pose_data/local_io.py
process_pose_data/overlay.py
process_pose_data/process.py
process_pose_data/shared_constants.py
process_pose_data/viz_3d.py
wf_process_pose_data-6.3.0.dist-info/LICENSE
wf_process_pose_data-6.3.0.dist-info/METADATA
wf_process_pose_data-6.3.0.dist-info/WHEEL
wf_process_pose_data-6.3.0.dist-info/top_level.txt
wf_process_pose_data-6.3.0.dist-info/RECORD
