Metadata-Version: 2.1
Name: wf-process-pose-data
Version: 6.3.0
Summary: Tools for fetching, processing, visualizing, and analyzing Wildflower human pose data
Home-page: https://github.com/WildflowerSchools/wf-process-pose-data
Author: Theodore Quinn
Author-email: ted.quinn@wildflowerschools.org
License: UNKNOWN
Keywords: pose reconstruction,pose tracking
Platform: UNKNOWN
Classifier: Intended Audience :: Developers
Classifier: License :: OSI Approved :: MIT License
Classifier: Operating System :: OS Independent
Classifier: Programming Language :: Python
License-File: LICENSE
Requires-Dist: wf-honeycomb-io (>=0.0.1)
Requires-Dist: wf-pose-db-io (>=0.1.1)
Requires-Dist: wf-cv-utils (>=3.0.0)
Requires-Dist: wf-video-io (>=1.0.0)
Requires-Dist: wf-geom-render (>=0.3.0)
Requires-Dist: poseconnect (>=0.1.0)
Requires-Dist: pandas (>=1.2.2)
Requires-Dist: numpy (>=1.20.1)
Requires-Dist: opencv-python (>=4.5.1)
Requires-Dist: matplotlib (>=3.3.4)
Requires-Dist: seaborn (>=0.11.1)
Requires-Dist: ffmpeg-python (>=0.2.0)
Requires-Dist: tqdm (>=4.57.0)
Requires-Dist: python-slugify (>=4.0.1)
Requires-Dist: python-dateutil (>=2.8)
